{
  "books": [
    {
      "id": "gen",
      "name": "اَلتَّكْوِينُ"
    },
    {
      "id": "exo",
      "name": "اَلْخُرُوجُ"
    },
    {
      "id": "lev",
      "name": "اَللَّاوِيِّينَ"
    },
    {
      "id": "num",
      "name": "اَلْعَدَد"
    },
    {
      "id": "deu",
      "name": "اَلتَّثْنِيَة"
    },
    {
      "id": "jos",
      "name": "يَشُوع"
    },
    {
      "id": "jdg",
      "name": "اَلْقُضَاة"
    },
    {
      "id": "rut",
      "name": "رَاعُوث"
    },
    {
      "id": "1sa",
      "name": "صَمُوئِيلَ ٱلْأَوَّلُ"
    },
    {
      "id": "2sa",
      "name": "صَمُوئِيلَ ٱلثَّانِي"
    },
    {
      "id": "1ki",
      "name": "اَلْمُلُوكِ ٱلْأَوَّلُ"
    },
    {
      "id": "2ki",
      "name": "اَلْمُلُوكِ ٱلثَّانِي"
    },
    {
      "id": "1ch",
      "name": "أَخْبَارِ ٱلْأَوَّلُ"
    },
    {
      "id": "2ch",
      "name": "أَخْبَارِ ٱلثَّانِي"
    },
    {
      "id": "ezr",
      "name": "عَزْرَا"
    },
    {
      "id": "neh",
      "name": "نَحَمْيَا"
    },
    {
      "id": "est",
      "name": "أَسْتِير"
    },
    {
      "id": "job",
      "name": "أَيُّوبَ"
    },
    {
      "id": "psa",
      "name": "اَلْمَزَامِيرُ"
    },
    {
      "id": "pro",
      "name": "أَمْثَالٌ"
    },
    {
      "id": "ecc",
      "name": "اَلْجَامِعَةِ"
    },
    {
      "id": "sng",
      "name": "نَشِيدُ ٱلْأَنْشَادِ"
    },
    {
      "id": "isa",
      "name": "إِشَعْيَاءَ"
    },
    {
      "id": "jer",
      "name": "إِرْمِيَا"
    },
    {
      "id": "lam",
      "name": "مَرَاثِي إِرْمِيَا"
    },
    {
      "id": "ezk",
      "name": "حِزْقِيَال"
    },
    {
      "id": "dan",
      "name": "دَانِيآل"
    },
    {
      "id": "hos",
      "name": "هُوشَع"
    },
    {
      "id": "jol",
      "name": "يُوئِيل"
    },
    {
      "id": "amo",
      "name": "عَامُوس"
    },
    {
      "id": "oba",
      "name": "عُوبَدْيَا"
    },
    {
      "id": "jon",
      "name": "يُونَان"
    },
    {
      "id": "mic",
      "name": "مِيخَا"
    },
    {
      "id": "nam",
      "name": "نَاحُوم"
    },
    {
      "id": "hab",
      "name": "حَبَقُّوق"
    },
    {
      "id": "zep",
      "name": "صَفَنْيَا"
    },
    {
      "id": "hag",
      "name": "حَجَّي"
    },
    {
      "id": "zec",
      "name": "زَكَريَّا"
    },
    {
      "id": "mal",
      "name": "مَلَاخِي"
    },
    {
      "id": "mat",
      "name": "مَتَّى"
    },
    {
      "id": "mrk",
      "name": "مَرْقُسَ"
    },
    {
      "id": "luk",
      "name": "لُوقَا"
    },
    {
      "id": "jhn",
      "name": "يُوحَنَّا"
    },
    {
      "id": "act",
      "name": "أَعْمَالُ ٱلرُّسُلِ"
    },
    {
      "id": "rom",
      "name": "رُومِيَةَ"
    },
    {
      "id": "1co",
      "name": "كُورِنْثُوسَ ٱلأُولَى"
    },
    {
      "id": "2co",
      "name": "كُورِنْثُوسَ ٱلثَّانِيةُ"
    },
    {
      "id": "gal",
      "name": "غَلَاطِيَّةَ"
    },
    {
      "id": "eph",
      "name": "أَفَسُسَ"
    },
    {
      "id": "php",
      "name": "فِيلِبِّي"
    },
    {
      "id": "col",
      "name": "كُولُوسِّي"
    },
    {
      "id": "1th",
      "name": "تَسَالُونِيكِي ٱلأُولَى"
    },
    {
      "id": "2th",
      "name": "تَسَالُونِيكِي ٱلثَّانِيةُ"
    },
    {
      "id": "1ti",
      "name": "تِيمُوثَاوُسَ ٱلْأُولَى"
    },
    {
      "id": "2ti",
      "name": "تِيمُوثَاوُسَ ٱلثَّانِيةُ"
    },
    {
      "id": "tit",
      "name": "تِيطُسَ"
    },
    {
      "id": "phm",
      "name": "فِلِيمُونَ"
    },
    {
      "id": "heb",
      "name": "ٱلْعِبْرَانِيِّينَ"
    },
    {
      "id": "jas",
      "name": "يَعْقُوبَ"
    },
    {
      "id": "1pe",
      "name": "بُطْرُسَ ٱلْأُولَى"
    },
    {
      "id": "2pe",
      "name": "بُطْرُسَ ٱلثَّانِيَةُ"
    },
    {
      "id": "1jn",
      "name": "يُوحَنَّا ٱلْأُولَى"
    },
    {
      "id": "2jn",
      "name": "يُوحَنَّا ٱلثَّانِيَةُ"
    },
    {
      "id": "3jn",
      "name": "يُوحَنَّا ٱلثَّالِثَةُ"
    },
    {
      "id": "jud",
      "name": "يَهُوذَا"
    },
    {
      "id": "rev",
      "name": "رُؤْيَا يُوحَنَّا"
    }
  ],
  "default_version": 13,
  "language": {
    "id": "arb",
    "name": "العربية"
  },
  "versions": [
    {
      "full_name": "الكتاب المقدس",
      "id": 13,
      "name": "AVD"
    },
    {
      "full_name": "الكتاب المقدس  (تخفيف تشكيل)",
      "id": 14,
      "name": "AVDDV"
    },
    {
      "full_name": "الترجمة العربية المشتركة",
      "id": 67,
      "name": "المشتركة"
    },
    {
      "full_name": "كتاب الحياة",
      "id": 101,
      "name": "KEH"
    },
    {
      "full_name": "Sharif Arabic Bible",
      "id": 153,
      "name": "SAB"
    },
    {
      "full_name": "الكِتاب المُقَدَّس: التَّرْجَمَةُ العَرَبِيَّةُ المُبَسَّطَةُ",
      "id": 195,
      "name": "ت ع م"
    },
    {
      "full_name": "المعنى الصحيح لإنجيل المسيح",
      "id": 1714,
      "name": "TMA"
    },
    {
      "full_name": "الترجمة الكاثوليكيّة (اليسوعيّة)",
      "id": 1981,
      "name": "ت.ك.ع"
    },
    {
      "full_name": "مزامير داود النبيّ - ترجمة الأب عفيف عسيران",
      "id": 2301,
      "name": "FAOV"
    },
    {
      "full_name": "Mediterranean Arabic Translation",
      "id": 2427,
      "name": "MAT"
    },
    {
      "full_name": "المعنى الصحيح لإنجيل المسيح - انشاد",
      "id": 3275,
      "name": "المعنى"
    }
  ]
}
