{
  "Using Helm": [
    {
      "title": "Quickstart",
      "url": "https://v2.helm.sh/docs/using_helm/#quickstart-guide"
    },
    {
      "title": "Installing Helm",
      "url": "https://v2.helm.sh/docs/using_helm/#installing-helm"
    },
    {
      "title": "Deprecated Kubernetes APIs",
      "url": "https://v2.helm.sh/docs/using_helm/#deprecated-kubernetes-apis"
    },
    {
      "title": "Kubernetes Distro Notes",
      "url": "https://v2.helm.sh/docs/using_helm/#kubernetes-distribution-guide"
    },
    {
      "title": "Install FAQ",
      "url": "https://v2.helm.sh/docs/using_helm/#installation-frequently-asked-questions"
    },
    {
      "title": "Using Helm",
      "url": "https://v2.helm.sh/docs/using_helm/#using-helm"
    },
    {
      "title": "Plugins",
      "url": "https://v2.helm.sh/docs/using_helm/#the-helm-plugins-guide"
    },
    {
      "title": "Role-Based Access Control",
      "url": "https://v2.helm.sh/docs/using_helm/#role-based-access-control"
    },
    {
      "title": "TLS/SSL for Helm and Tiller",
      "url": "https://v2.helm.sh/docs/using_helm/#using-ssl-between-helm-and-tiller"
    },
    {
      "title": "Securing your Helm Installation",
      "url": "https://v2.helm.sh/docs/using_helm/#securing-your-helm-installation"
    }
  ],
  "Helm Commands": [
    {
      "title": "Helm",
      "url": "https://v2.helm.sh/docs/helm/#helm"
    },
    {
      "title": "Helm Completion",
      "url": "https://v2.helm.sh/docs/helm/#helm-completion"
    },
    {
      "title": "Helm Create",
      "url": "https://v2.helm.sh/docs/helm/#helm-create"
    },
    {
      "title": "Helm Delete",
      "url": "https://v2.helm.sh/docs/helm/#helm-delete"
    },
    {
      "title": "Helm Dependency",
      "url": "https://v2.helm.sh/docs/helm/#helm-dependency"
    },
    {
      "title": "Helm Dependency Build",
      "url": "https://v2.helm.sh/docs/helm/#helm-dependency-build"
    },
    {
      "title": "Helm Dependency List",
      "url": "https://v2.helm.sh/docs/helm/#helm-dependency-list"
    },
    {
      "title": "Helm Dependency Update",
      "url": "https://v2.helm.sh/docs/helm/#helm-dependency-update"
    },
    {
      "title": "Helm Fetch",
      "url": "https://v2.helm.sh/docs/helm/#helm-fetch"
    },
    {
      "title": "Helm Get",
      "url": "https://v2.helm.sh/docs/helm/#helm-get"
    },
    {
      "title": "Helm Get Hooks",
      "url": "https://v2.helm.sh/docs/helm/#helm-get-hooks"
    },
    {
      "title": "Helm Get Manifest",
      "url": "https://v2.helm.sh/docs/helm/#helm-get-manifest"
    },
    {
      "title": "Helm Get Values",
      "url": "https://v2.helm.sh/docs/helm/#helm-get-values"
    },
    {
      "title": "Helm History",
      "url": "https://v2.helm.sh/docs/helm/#helm-history"
    },
    {
      "title": "Helm Home",
      "url": "https://v2.helm.sh/docs/helm/#helm-home"
    },
    {
      "title": "Helm Init",
      "url": "https://v2.helm.sh/docs/helm/#helm-init"
    },
    {
      "title": "Helm Inspect",
      "url": "https://v2.helm.sh/docs/helm/#helm-inspect"
    },
    {
      "title": "Helm Inspect Chart",
      "url": "https://v2.helm.sh/docs/helm/#helm-inspect-chart"
    },
    {
      "title": "Helm Inspect Values",
      "url": "https://v2.helm.sh/docs/helm/#helm-inspect-values"
    },
    {
      "title": "Helm Install",
      "url": "https://v2.helm.sh/docs/helm/#helm-install"
    },
    {
      "title": "Helm Lint",
      "url": "https://v2.helm.sh/docs/helm/#helm-lint"
    },
    {
      "title": "Helm List",
      "url": "https://v2.helm.sh/docs/helm/#helm-list"
    },
    {
      "title": "Helm Package",
      "url": "https://v2.helm.sh/docs/helm/#helm-package"
    },
    {
      "title": "Helm Plugin",
      "url": "https://v2.helm.sh/docs/helm/#helm-plugin"
    },
    {
      "title": "Helm Plugin Install",
      "url": "https://v2.helm.sh/docs/helm/#helm-plugin-install"
    },
    {
      "title": "Helm Plugin List",
      "url": "https://v2.helm.sh/docs/helm/#helm-plugin-list"
    },
    {
      "title": "Helm Plugin Remove",
      "url": "https://v2.helm.sh/docs/helm/#helm-plugin-remove"
    },
    {
      "title": "Helm Plugin Update",
      "url": "https://v2.helm.sh/docs/helm/#helm-plugin-update"
    },
    {
      "title": "Helm Repo",
      "url": "https://v2.helm.sh/docs/helm/#helm-repo"
    },
    {
      "title": "Helm Repo Add",
      "url": "https://v2.helm.sh/docs/helm/#helm-repo-add"
    },
    {
      "title": "Helm Repo Index",
      "url": "https://v2.helm.sh/docs/helm/#helm-repo-index"
    },
    {
      "title": "Helm Repo List",
      "url": "https://v2.helm.sh/docs/helm/#helm-rep-list"
    },
    {
      "title": "Helm Repo Remove",
      "url": "https://v2.helm.sh/docs/helm/#helm-repo-remove"
    },
    {
      "title": "Helm Repo Update",
      "url": "https://v2.helm.sh/docs/helm/#helm-repo-update"
    },
    {
      "title": "Helm Reset",
      "url": "https://v2.helm.sh/docs/helm/#helm-reset"
    },
    {
      "title": "Helm Rollback",
      "url": "https://v2.helm.sh/docs/helm/#helm-rollback"
    },
    {
      "title": "Helm Search",
      "url": "https://v2.helm.sh/docs/helm/#helm-search"
    },
    {
      "title": "Helm Serve",
      "url": "https://v2.helm.sh/docs/helm/#helm-serve"
    },
    {
      "title": "Helm Status",
      "url": "https://v2.helm.sh/docs/helm/#helm-status"
    },
    {
      "title": "Helm Template",
      "url": "https://v2.helm.sh/docs/helm/#helm-template"
    },
    {
      "title": "Helm Test",
      "url": "https://v2.helm.sh/docs/helm/#helm-test"
    },
    {
      "title": "Helm Upgrade",
      "url": "https://v2.helm.sh/docs/helm/#helm-upgrade"
    },
    {
      "title": "Helm Verify",
      "url": "https://v2.helm.sh/docs/helm/#helm-verify"
    },
    {
      "title": "Helm Version",
      "url": "https://v2.helm.sh/docs/helm/#helm-version"
    }
  ],
  "Charts": [
    {
      "title": "Intro to Charts",
      "url": "https://v2.helm.sh/docs/developing_charts/#charts"
    },
    {
      "title": "Chart Lifecycle Hooks",
      "url": "https://v2.helm.sh/docs/developing_charts/#hooks"
    },
    {
      "title": "Charts Tips and Tricks",
      "url": "https://v2.helm.sh/docs/developing_charts/#chart-development-tips-and-tricks"
    },
    {
      "title": "Charts Repository Guide",
      "url": "https://v2.helm.sh/docs/developing_charts/#the-chart-repository-guide"
    },
    {
      "title": "Syncing Your Chart Repo",
      "url": "https://v2.helm.sh/docs/developing_charts/#syncing-your-chart-repository"
    },
    {
      "title": "Signing Charts",
      "url": "https://v2.helm.sh/docs/developing_charts/#helm-provenance-and-integrity"
    },
    {
      "title": "Chart Tests",
      "url": "https://v2.helm.sh/docs/developing_charts/#chart-tests"
    },
    {
      "title": "Chart Repository FAQ",
      "url": "https://v2.helm.sh/docs/developing_charts/#chart-repositories-frequently-asked-questions"
    }
  ],
  "Developing Templates": [
    {
      "title": "Intro",
      "url": "https://v2.helm.sh/docs/chart_template_guide/#the-chart-template-developer-s-guide"
    },
    {
      "title": "Getting Started",
      "url": "https://v2.helm.sh/docs/chart_template_guide/#getting-started-with-a-chart-template"
    },
    {
      "title": "Built-In Objects",
      "url": "https://v2.helm.sh/docs/chart_template_guide/#built-in-objects"
    },
    {
      "title": "Values Files",
      "url": "https://v2.helm.sh/docs/chart_template_guide/#values-files"
    },
    {
      "title": "Template Functions and Pipelines",
      "url": "https://v2.helm.sh/docs/chart_template_guide/#template-functions-and-pipelines"
    },
    {
      "title": "Flow Control",
      "url": "https://v2.helm.sh/docs/chart_template_guide/#flow-control"
    },
    {
      "title": "Variables",
      "url": "https://v2.helm.sh/docs/chart_template_guide/#variables"
    },
    {
      "title": "Named Templates",
      "url": "https://v2.helm.sh/docs/chart_template_guide/#named-templates"
    },
    {
      "title": "Accessing Files Inside Templates",
      "url": "https://v2.helm.sh/docs/chart_template_guide/#accessing-files-inside-templates"
    },
    {
      "title": "Creating a NOTES.txt File",
      "url": "https://v2.helm.sh/docs/chart_template_guide/#creating-a-notes-txt-file"
    },
    {
      "title": "Subcharts and Global Values",
      "url": "https://v2.helm.sh/docs/chart_template_guide/#subcharts-and-global-values"
    },
    {
      "title": "The .helmignore File",
      "url": "https://v2.helm.sh/docs/chart_template_guide/#the-helmignore-file"
    },
    {
      "title": "Debugging Templates",
      "url": "https://v2.helm.sh/docs/chart_template_guide/#debugging-templates"
    },
    {
      "title": "Next Steps",
      "url": "https://v2.helm.sh/docs/chart_template_guide/#wrapping-up"
    },
    {
      "title": "Appendix: YAML Techniques",
      "url": "https://v2.helm.sh/docs/chart_template_guide/#yaml-techniques"
    },
    {
      "title": "Appendix: Go Data Types and Templates",
      "url": "https://v2.helm.sh/docs/chart_template_guide/#appendix-go-data-types-and-templates"
    }
  ],
  "Best Practices": [
    {
      "title": "Intro",
      "url": "https://v2.helm.sh/docs/chart_best_practices/#the-chart-best-practices-guide"
    },
    {
      "title": "General Conventions",
      "url": "https://v2.helm.sh/docs/chart_best_practices/#general-conventions"
    },
    {
      "title": "Values",
      "url": "https://v2.helm.sh/docs/chart_best_practices/#values"
    },
    {
      "title": "Templates",
      "url": "https://v2.helm.sh/docs/chart_best_practices/#templates"
    },
    {
      "title": "Requirements",
      "url": "https://v2.helm.sh/docs/chart_best_practices/#requirements-files"
    },
    {
      "title": "Labels &amp; Annotations",
      "url": "https://v2.helm.sh/docs/chart_best_practices/#labels-and-annotations"
    },
    {
      "title": "Pods &amp; PodTemplates",
      "url": "https://v2.helm.sh/docs/chart_best_practices/#pods-and-podtemplates"
    },
    {
      "title": "Custom Resource Definitions",
      "url": "https://v2.helm.sh/docs/chart_best_practices/#custom-resource-definitions"
    },
    {
      "title": "RBAC",
      "url": "https://v2.helm.sh/docs/chart_best_practices/#role-based-access-control"
    }
  ]
}
