{
  "chromium": [
    {
      "app": "Google Chrome",
      "type": "CHROMIUM",
      "title": "Google Chrome",
      "path": "/Library/Application Support/Google/Chrome",
      "icon": "chrome.png"
    },
    {
      "app": "Google Chrome Dev",
      "type": "CHROMIUM",
      "title": "Google Chrome Dev",
      "path": "/Library/Application Support/Google/Chrome Dev",
      "icon": "chrome-dev.png"
    },
    {
      "app": "Google Chrome Canary",
      "type": "CHROMIUM",
      "title": "Google Chrome Canary",
      "path": "/Library/Application Support/Google/Chrome Canary",
      "icon": "canary.png"
    },
    {
      "app": "Chromium",
      "type": "CHROMIUM",
      "title": "Chromium",
      "path": "/Library/Application Support/Chromium",
      "icon": "chromium.png"
    },
    {
      "app": "Brave Browser",
      "type": "CHROMIUM",
      "title": "Brave",
      "path": "/Library/Application Support/BraveSoftware/Brave-Browser",
      "icon": "brave.png"
    },
    {
      "app": "Microsoft Edge",
      "type": "CHROMIUM",
      "title": "Microsoft Edge",
      "path": "/Library/Application Support/Microsoft Edge",
      "icon": "edge.png"
    },
    {
      "app": "Microsoft Edge Dev",
      "type": "CHROMIUM",
      "title": "Microsoft Edge Dev",
      "path": "/Library/Application Support/Microsoft Edge Dev",
      "icon": "edge-dev.png"
    },
    {
      "app": "Microsoft Edge Canary",
      "type": "CHROMIUM",
      "title": "Microsoft Edge Canary",
      "path": "/Library/Application Support/Microsoft Edge Canary",
      "icon": "edge-canary.png"
    }
  ],
  "firefox": [
    {
      "app": "/Applications/Firefox.app/Contents/MacOS/firefox",
      "type": "FIREFOX",
      "title": "Firefox",
      "path": "/Library/Application Support/Firefox",
      "icon": "firefox.png"
    },
    {
      "app": "/Applications/Firefox Developer Edition.app/Contents/MacOS/firefox",
      "type": "FIREFOX",
      "title": "Firefox Developer Edition",
      "path": "/Library/Application Support/Firefox",
      "icon": "firefox-dev.png"
    },
    {
      "app": "/Applications/Firefox Nightly.app/Contents/MacOS/firefox",
      "type": "FIREFOX",
      "title": "Firefox Nightly",
      "path": "/Library/Application Support/Firefox",
      "icon": "firefox-nightly.png"
    }
  ]
}
