[
  { "name": "NADESHIKO", "colorCode": "#DC9FB4" },
  { "name": "KOHBAI", "colorCode": "#E16B8C" },
  { "name": "SUOH", "colorCode": "#8E354A" },
  { "name": "TAIKOH", "colorCode": "#F8C3CD" },
  { "name": "IKKONZOME", "colorCode": "#F4A7B9" },
  { "name": "KUWAZOME", "colorCode": "#64363C" },
  { "name": "MOMO", "colorCode": "#F596AA" },
  { "name": "ICHIGO", "colorCode": "#B5495B" },
  { "name": "USUBENI", "colorCode": "#E87A90" },
  { "name": "IMAYOH", "colorCode": "#D05A6E" },
  { "name": "NAKABENI", "colorCode": "#DB4D6D" },
  { "name": "SAKURA", "colorCode": "#FEDFE1" },
  { "name": "UMENEZUMI", "colorCode": "#9E7A7A" },
  { "name": "KARAKURENAI", "colorCode": "#D0104C" },
  { "name": "ENJI", "colorCode": "#9F353A" },
  { "name": "KURENAI", "colorCode": "#CB1B45" },
  { "name": "TOKI", "colorCode": "#EEA9A9" },
  { "name": "CYOHSYUN", "colorCode": "#BF6766" },
  { "name": "KOKIAKE", "colorCode": "#86473F" },
  { "name": "SAKURANEZUMI", "colorCode": "#B19693" },
  { "name": "JINZAMOMI", "colorCode": "#EB7A77" },
  { "name": "AZUKI", "colorCode": "#954A45" },
  { "name": "SUOHKOH", "colorCode": "#A96360" },
  { "name": "AKABENI", "colorCode": "#CB4042" },
  { "name": "SHINSYU", "colorCode": "#AB3B3A" },
  { "name": "HAIZAKURA", "colorCode": "#D7C4BB" },
  { "name": "KURIUME", "colorCode": "#904840" },
  { "name": "EBICHA", "colorCode": "#734338" },
  { "name": "GINSYU", "colorCode": "#C73E3A" },
  { "name": "KUROTOBI", "colorCode": "#554236" },
  { "name": "BENITOBI", "colorCode": "#994639" },
  { "name": "AKEBONO", "colorCode": "#F19483" },
  { "name": "BENIKABA", "colorCode": "#B54434" },
  { "name": "MIZUGAKI", "colorCode": "#B9887D" },
  { "name": "SANGOSYU", "colorCode": "#F17C67" },
  { "name": "BENIHIWADA", "colorCode": "#884C3A" },
  { "name": "SYOJYOHI", "colorCode": "#E83015" },
  { "name": "ENTAN", "colorCode": "#D75455" },
  { "name": "SHIKANCHA", "colorCode": "#B55D4C" },
  { "name": "HIWADA", "colorCode": "#854836" },
  { "name": "KAKISHIBU", "colorCode": "#A35E47" },
  { "name": "AKE", "colorCode": "#CC543A" },
  { "name": "TOBI", "colorCode": "#724832" },
  { "name": "BENIHI", "colorCode": "#F75C2F" },
  { "name": "KURIKAWACHA", "colorCode": "#6A4028" },
  { "name": "BENGARA", "colorCode": "#9A5034" },
  { "name": "TERIGAKI", "colorCode": "#C46243" },
  { "name": "EDOCHA", "colorCode": "#AF5F3C" },
  { "name": "ARAISYU", "colorCode": "#FB966E" },
  { "name": "MOMOSHIOCHA", "colorCode": "#724938" },
  { "name": "KARACHA", "colorCode": "#B47157" },
  { "name": "TOKIGARACHA", "colorCode": "#DB8E71" },
  { "name": "OHNI", "colorCode": "#F05E1C" },
  { "name": "SOHI", "colorCode": "#ED784A" },
  { "name": "ENSYUCHA", "colorCode": "#CA7853" },
  { "name": "KABACHA", "colorCode": "#B35C37" },
  { "name": "KOGECHA", "colorCode": "#563F2E" },
  { "name": "AKAKOH", "colorCode": "#E3916E" },
  { "name": "SUZUMECHA", "colorCode": "#8F5A3C" },
  { "name": "SHISHI", "colorCode": "#F0A986" },
  { "name": "SODENKARACHA", "colorCode": "#A0674B" },
  { "name": "KABA", "colorCode": "#C1693C" },
  { "name": "KOKIKUCHINASHI", "colorCode": "#FB9966" },
  { "name": "KURUMI", "colorCode": "#947A6D" },
  { "name": "TAISYA", "colorCode": "#A36336" },
  { "name": "ARAIGAKI", "colorCode": "#E79460" },
  { "name": "KOHROZEN", "colorCode": "#7D532C" },
  { "name": "AKAKUCHIBA", "colorCode": "#C78550" },
  { "name": "TONOCHA", "colorCode": "#985F2A" },
  { "name": "AKASHIROTSURUBAMI", "colorCode": "#E1A679" },
  { "name": "SENCHA", "colorCode": "#855B32" },
  { "name": "KANZO", "colorCode": "#FC9F4D" },
  { "name": "SHAREGAKI", "colorCode": "#FFBA84" },
  { "name": "BENIUKON", "colorCode": "#E98B2A" },
  { "name": "UMEZOME", "colorCode": "#E9A368" },
  { "name": "BIWACHA", "colorCode": "#B17844" },
  { "name": "CHOJICHA", "colorCode": "#96632E" },
  { "name": "KENPOHZOME", "colorCode": "#43341B" },
  { "name": "KOHAKU", "colorCode": "#CA7A2C" },
  { "name": "USUGAKI", "colorCode": "#ECB88A" },
  { "name": "KYARA", "colorCode": "#78552B" },
  { "name": "CHOJIZOME", "colorCode": "#B07736" },
  { "name": "FUSHIZOME", "colorCode": "#967249" },
  { "name": "KUCHIBA", "colorCode": "#E2943B" },
  { "name": "KINCHA", "colorCode": "#C7802D" },
  { "name": "KITSUNE", "colorCode": "#9B6E23" },
  { "name": "SUSUTAKE", "colorCode": "#6E552F" },
  { "name": "USUKOH", "colorCode": "#EBB471" },
  { "name": "TONOKO", "colorCode": "#D7B98E" },
  { "name": "GINSUSUTAKE", "colorCode": "#82663A" },
  { "name": "OHDO", "colorCode": "#B68E55" },
  { "name": "SHIRACHA", "colorCode": "#BC9F77" },
  { "name": "KOBICHA", "colorCode": "#876633" },
  { "name": "KIGARACHA", "colorCode": "#C18A26" },
  { "name": "YAMABUKI", "colorCode": "#FFB11B" },
  { "name": "YAMABUKICHA", "colorCode": "#D19826" },
  { "name": "HAJIZOME", "colorCode": "#DDA52D" },
  { "name": "KUWACHA", "colorCode": "#C99833" },
  { "name": "TAMAGO", "colorCode": "#F9BF45" },
  { "name": "SHIROTSURUBAMI", "colorCode": "#DCB879" },
  { "name": "KITSURUBAMI", "colorCode": "#BA9132" },
  { "name": "TAMAMOROKOSHI", "colorCode": "#E8B647" },
  { "name": "HANABA", "colorCode": "#F7C242" },
  { "name": "NAMAKABE", "colorCode": "#7D6C46" },
  { "name": "TORINOKO", "colorCode": "#DAC9A6" },
  { "name": "USUKI", "colorCode": "#FAD689" },
  { "name": "KIKUCHIBA", "colorCode": "#D9AB42" },
  { "name": "KUCHINASHI", "colorCode": "#F6C555" },
  { "name": "TOHOH", "colorCode": "#FFC408" },
  { "name": "UKON", "colorCode": "#EFBB24" },
  { "name": "KARASHI", "colorCode": "#CAAD5F" },
  { "name": "HIGOSUSUTAKE", "colorCode": "#8D742A" },
  { "name": "RIKYUSHIRACHA", "colorCode": "#B4A582" },
  { "name": "AKU", "colorCode": "#877F6C" },
  { "name": "RIKYUCHA", "colorCode": "#897D55" },
  { "name": "ROKOHCHA", "colorCode": "#74673E" },
  { "name": "NATANEYU", "colorCode": "#A28C37" },
  { "name": "UGUISUCHA", "colorCode": "#6C6024" },
  { "name": "KIMIRUCHA", "colorCode": "#867835" },
  { "name": "MIRUCHA", "colorCode": "#62592C" },
  { "name": "KARIYASU", "colorCode": "#E9CD4C" },
  { "name": "NANOHANA", "colorCode": "#F7D94C" },
  { "name": "KIHADA", "colorCode": "#FBE251" },
  { "name": "MUSHIKURI", "colorCode": "#D9CD90" },
  { "name": "AOKUCHIBA", "colorCode": "#ADA142" },
  { "name": "OMINAESHI", "colorCode": "#DDD23B" },
  { "name": "HIWACHA", "colorCode": "#A5A051" },
  { "name": "HIWA", "colorCode": "#BEC23F" },
  { "name": "UGUISU", "colorCode": "#6C6A2D" },
  { "name": "YANAGICHA", "colorCode": "#939650" },
  { "name": "KOKE", "colorCode": "#838A2D" },
  { "name": "KIKUJIN", "colorCode": "#B1B479" },
  { "name": "RIKANCHA", "colorCode": "#616138" },
  { "name": "AIKOBICHA", "colorCode": "#4B4E2A" },
  { "name": "MIRU", "colorCode": "#5B622E" },
  { "name": "SENSAICHA", "colorCode": "#4D5139" },
  { "name": "BAIKOCHA", "colorCode": "#89916B" },
  { "name": "HIWAMOEGI", "colorCode": "#90B44B" },
  { "name": "YANAGIZOME", "colorCode": "#91AD70" },
  { "name": "URAYANAGI", "colorCode": "#B5CAA0" },
  { "name": "IWAICHA", "colorCode": "#646A58" },
  { "name": "MOEGI", "colorCode": "#7BA23F" },
  { "name": "NAE", "colorCode": "#86C166" },
  { "name": "YANAGISUSUTAKE", "colorCode": "#4A593D" },
  { "name": "MATSUBA", "colorCode": "#42602D" },
  { "name": "AONI", "colorCode": "#516E41" },
  { "name": "USUAO", "colorCode": "#91B493" },
  { "name": "YANAGINEZUMI", "colorCode": "#808F7C" },
  { "name": "TOKIWA", "colorCode": "#1B813E" },
  { "name": "WAKATAKE", "colorCode": "#5DAC81" },
  { "name": "CHITOSEMIDORI", "colorCode": "#36563C" },
  { "name": "MIDORI", "colorCode": "#227D51" },
  { "name": "BYAKUROKU", "colorCode": "#A8D8B9" },
  { "name": "OITAKE", "colorCode": "#6A8372" },
  { "name": "TOKUSA", "colorCode": "#2D6D4B" },
  { "name": "ONANDOCHA", "colorCode": "#465D4C" },
  { "name": "ROKUSYOH", "colorCode": "#24936E" },
  { "name": "SABISEIJI", "colorCode": "#86A697" },
  { "name": "AOTAKE", "colorCode": "#00896C" },
  { "name": "VELUDO", "colorCode": "#096148" },
  { "name": "MUSHIAO", "colorCode": "#20604F" },
  { "name": "AIMIRUCHA", "colorCode": "#0F4C3A" },
  { "name": "TONOCHA2", "colorCode": "#4F726C" },
  { "name": "AOMIDORI", "colorCode": "#00AA90" },
  { "name": "SEIJI", "colorCode": "#69B0AC" },
  { "name": "TETSU", "colorCode": "#26453D" },
  { "name": "MIZUASAGI", "colorCode": "#66BAB7" },
  { "name": "SEIHEKI", "colorCode": "#268785" },
  { "name": "SABITETSUONANDO", "colorCode": "#405B55" },
  { "name": "KORAINANDO", "colorCode": "#305A56" },
  { "name": "BYAKUGUN", "colorCode": "#78C2C4" },
  { "name": "OMESHICHA", "colorCode": "#376B6D" },
  { "name": "KAMENOZOKI", "colorCode": "#A5DEE4" },
  { "name": "FUKAGAWANEZUMI", "colorCode": "#77969A" },
  { "name": "SABIASAGI", "colorCode": "#6699A1" },
  { "name": "MIZU", "colorCode": "#81C7D4" },
  { "name": "ASAGI", "colorCode": "#33A6B8" },
  { "name": "ONANDO", "colorCode": "#0C4842" },
  { "name": "AI", "colorCode": "#0D5661" },
  { "name": "SHINBASHI", "colorCode": "#0089A7" },
  { "name": "SABIONANDO", "colorCode": "#336774" },
  { "name": "TETSUONANDO", "colorCode": "#255359" },
  { "name": "HANAASAGI", "colorCode": "#1E88A8" },
  { "name": "AINEZUMI", "colorCode": "#566C73" },
  { "name": "MASUHANA", "colorCode": "#577C8A" },
  { "name": "SORA", "colorCode": "#58B2DC" },
  { "name": "NOSHIMEHANA", "colorCode": "#2B5F75" },
  { "name": "CHIGUSA", "colorCode": "#3A8FB7" },
  { "name": "OMESHIONANDO", "colorCode": "#2E5C6E" },
  { "name": "HANADA", "colorCode": "#006284" },
  { "name": "WASURENAGUSA", "colorCode": "#7DB9DE" },
  { "name": "GUNJYO", "colorCode": "#51A8DD" },
  { "name": "TSUYUKUSA", "colorCode": "#2EA9DF" },
  { "name": "KUROTSURUBAMI", "colorCode": "#0B1013" },
  { "name": "KON", "colorCode": "#0F2540" },
  { "name": "KACHI", "colorCode": "#08192D" },
  { "name": "RURI", "colorCode": "#005CAF" },
  { "name": "RURIKON", "colorCode": "#0B346E" },
  { "name": "BENIMIDORI", "colorCode": "#7B90D2" },
  { "name": "FUJINEZUMI", "colorCode": "#6E75A4" },
  { "name": "TETSUKON", "colorCode": "#261E47" },
  { "name": "KONJYO", "colorCode": "#113285" },
  { "name": "BENIKAKEHANA", "colorCode": "#4E4F97" },
  { "name": "KONKIKYO", "colorCode": "#211E55" },
  { "name": "FUJI", "colorCode": "#8B81C3" },
  { "name": "FUTAAI", "colorCode": "#70649A" },
  { "name": "OUCHI", "colorCode": "#9B90C2" },
  { "name": "FUJIMURASAKI", "colorCode": "#8A6BBE" },
  { "name": "KIKYO", "colorCode": "#6A4C9C" },
  { "name": "SHION", "colorCode": "#8F77B5" },
  { "name": "MESSHI", "colorCode": "#533D5B" },
  { "name": "USU", "colorCode": "#B28FCE" },
  { "name": "HASHITA", "colorCode": "#986DB2" },
  { "name": "EDOMURASAKI", "colorCode": "#77428D" },
  { "name": "SHIKON", "colorCode": "#3C2F41" },
  { "name": "KOKIMURASAKI", "colorCode": "#4A225D" },
  { "name": "SUMIRE", "colorCode": "#66327C" },
  { "name": "MURASAKI", "colorCode": "#592C63" },
  { "name": "AYAME", "colorCode": "#6F3381" },
  { "name": "FUJISUSUTAKE", "colorCode": "#574C57" },
  { "name": "BENIFUJI", "colorCode": "#B481BB" },
  { "name": "KUROBENI", "colorCode": "#3F2B36" },
  { "name": "NASUKON", "colorCode": "#572A3F" },
  { "name": "BUDOHNEZUMI", "colorCode": "#5E3D50" },
  { "name": "HATOBANEZUMI", "colorCode": "#72636E" },
  { "name": "KAKITSUBATA", "colorCode": "#622954" },
  { "name": "EBIZOME", "colorCode": "#6D2E5B" },
  { "name": "BOTAN", "colorCode": "#C1328E" },
  { "name": "UMEMURASAKI", "colorCode": "#A8497A" },
  { "name": "NISEMURASAKI", "colorCode": "#562E37" },
  { "name": "TSUTSUJI", "colorCode": "#E03C8A" },
  { "name": "MURASAKITOBI", "colorCode": "#60373E" },
  { "name": "SHIRONERI", "colorCode": "#FCFAF2" },
  { "name": "GOFUN", "colorCode": "#FFFFFB" },
  { "name": "SHIRONEZUMI", "colorCode": "#BDC0BA" },
  { "name": "GINNEZUMI", "colorCode": "#91989F" },
  { "name": "NAMARI", "colorCode": "#787878" },
  { "name": "HAI", "colorCode": "#828282" },
  { "name": "SUNEZUMI", "colorCode": "#787D7B" },
  { "name": "RIKYUNEZUMI", "colorCode": "#707C74" },
  { "name": "NIBI", "colorCode": "#656765" },
  { "name": "AONIBI", "colorCode": "#535953" },
  { "name": "DOBUNEZUMI", "colorCode": "#4F4F48" },
  { "name": "BENIKESHINEZUMI", "colorCode": "#52433D" },
  { "name": "AISUMICHA", "colorCode": "#373C38" },
  { "name": "BINROJIZOME", "colorCode": "#3A3226" },
  { "name": "KESHIZUMI", "colorCode": "#434343" },
  { "name": "SUMI", "colorCode": "#1C1C1C" },
  { "name": "KURO", "colorCode": "#080808" },
  { "name": "RO", "colorCode": "#0C0C0C" }
]
